_ncrystal_verify/__init__.py
_ncrystal_verify/_cli.py
_ncrystal_verify/data/data/Al_multirole.ncmat
_ncrystal_verify/data/data/Al_sg225_with_voids.ncmat
_ncrystal_verify/data/data/QE_pw_Al.out
_ncrystal_verify/data/data/Wyckoff1963_Sulphor_0011255.cif
_ncrystal_verify/data/data/downstream_cmake_CMakeLists.txt
_ncrystal_verify/data/data/downstream_cmake_main.cc
_ncrystal_verify/data/data/dummy_D.cif
_ncrystal_verify/data/data/fake_cod_1000257.cif
_ncrystal_verify/data/data/fake_cod_9005777.cif
_ncrystal_verify/data/data/fake_mp_55.cif
_ncrystal_verify/data/data/mp_55_unrefined_conventional.cif
_ncrystal_verify/data/data/mp_55_unrefined_primitive.cif
_ncrystal_verify/data/data/refnc1/Ag_sg225.ncmat
_ncrystal_verify/data/data/refnc1/Al2O3_sg167_Corundum.ncmat
_ncrystal_verify/data/data/refnc1/Al_sg225.ncmat
_ncrystal_verify/data/data/refnc1/Au_sg225.ncmat
_ncrystal_verify/data/data/refnc1/Ba_sg229.ncmat
_ncrystal_verify/data/data/refnc1/BeF2_sg152_Beryllium_Fluoride.ncmat
_ncrystal_verify/data/data/refnc1/Be_sg194.ncmat
_ncrystal_verify/data/data/refnc1/C_sg194_pyrolytic_graphite.ncmat
_ncrystal_verify/data/data/refnc1/C_sg227_Diamond.ncmat
_ncrystal_verify/data/data/refnc1/CaCO3_sg62_Aragonite.ncmat
_ncrystal_verify/data/data/refnc1/Ca_sg225.ncmat
_ncrystal_verify/data/data/refnc1/Ca_sg229_Calcium-gamma.ncmat
_ncrystal_verify/data/data/refnc1/Cr_sg229.ncmat
_ncrystal_verify/data/data/refnc1/Cu2O_sg224_Cuprite.ncmat
_ncrystal_verify/data/data/refnc1/Cu_sg225.ncmat
_ncrystal_verify/data/data/refnc1/Fe_sg229_Iron-alpha.ncmat
_ncrystal_verify/data/data/refnc1/Fe_sg229_Iron-beta.ncmat
_ncrystal_verify/data/data/refnc1/Ge_sg227.ncmat
_ncrystal_verify/data/data/refnc1/MgO_sg225_Periclase.ncmat
_ncrystal_verify/data/data/refnc1/Mg_sg194.ncmat
_ncrystal_verify/data/data/refnc1/Mo_sg229.ncmat
_ncrystal_verify/data/data/refnc1/Na4Si3Al3O12Cl_sg218_Sodalite.ncmat
_ncrystal_verify/data/data/refnc1/Na_sg229.ncmat
_ncrystal_verify/data/data/refnc1/Nb_sg229.ncmat
ncrystal_verify-4.2.12.dist-info/METADATA
ncrystal_verify-4.2.12.dist-info/WHEEL
ncrystal_verify-4.2.12.dist-info/entry_points.txt
ncrystal_verify-4.2.12.dist-info/licenses/LICENSE
ncrystal_verify-4.2.12.dist-info/RECORD
