Metadata-Version: 2.1
Name: ncrystal-verify
Version: 4.2.12
Summary: Library for thermal neutron transport in crystals and other materials.
Author: NCrystal developers (Thomas Kittelmann, Xiao Xiao Cai)
License: 
Classifier: Programming Language :: Python :: 3
Classifier: License :: OSI Approved :: Apache Software License
Project-URL: Homepage, https://mctools.github.io/ncrystal/
Project-URL: Bug Tracker, https://github.com/mctools/ncrystal/issues
Requires-Python: >=3.8
Requires-Dist: ncrystal-python==4.2.12
Provides-Extra: all
Requires-Dist: ase>=3.23.0; extra == "all"
Requires-Dist: endf-parserpy>=0.14.3; extra == "all"
Requires-Dist: gemmi>=0.6.1; extra == "all"
Requires-Dist: matplotlib>=3.6.0; extra == "all"
Requires-Dist: mpmath>=1.3.0; extra == "all"
Requires-Dist: numpy>=1.22; extra == "all"
Requires-Dist: spglib>=2.1.0; extra == "all"
